obsidian_index/__init__.py
obsidian_index/background_worker.py
obsidian_index/logger.py
obsidian_index/main.py
obsidian_index/mcp_server.py
obsidian_index/recent_notes.py
obsidian_index/index/__init__.py
obsidian_index/index/database.py
obsidian_index/index/encoder.py
obsidian_index/index/indexer.py
obsidian_index/index/messages.py
obsidian_index/index/searcher.py
obsidian_index/index/worker.py
iflow_mcp_tcsavage_obsidian_index-0.1.1.dist-info/METADATA
iflow_mcp_tcsavage_obsidian_index-0.1.1.dist-info/WHEEL
iflow_mcp_tcsavage_obsidian_index-0.1.1.dist-info/entry_points.txt
iflow_mcp_tcsavage_obsidian_index-0.1.1.dist-info/RECORD
