Metadata-Version: 2.4
Name: iflow-mcp_tcsavage_obsidian-index
Version: 0.1.1
Summary: An MCP server that provides a semantic search over an Obsidian vault
Author-email: Tom Savage <tcsavage@gmail.com>
Requires-Python: >=3.11
Requires-Dist: click>=8.1.7
Requires-Dist: duckdb>=1.1.3
Requires-Dist: mcp>=1.0.0
Requires-Dist: python-json-logger>=2.0.7
Requires-Dist: sentence-transformers>=3.3.1
Requires-Dist: watchdog>=6.0.0
